layeris/__init__.py
layeris/layer_image.py
layeris/test/__init__.py
layeris/test/test.py
layeris/utils/__init__.py
layeris/utils/channels.py
layeris/utils/conversions.py
layeris/utils/hsl.py
layeris/utils/layers.py
layeris-0.1.3.dist-info/LICENSE
layeris-0.1.3.dist-info/METADATA
layeris-0.1.3.dist-info/WHEEL
layeris-0.1.3.dist-info/top_level.txt
layeris-0.1.3.dist-info/RECORD
