Metadata-Version: 2.1
Name: layeris
Version: 0.1.3
Summary: An open source image processing library that supports blend modes, curve adjustment, and other adjustments that graphic designers or photographers frequently use
Home-page: https://github.com/subwaymatch/layer-is-python
Author: Ye Joo Park
Author-email: subwaymatch@gmail.com
License: UNKNOWN
Platform: UNKNOWN
Classifier: Programming Language :: Python :: 3
Classifier: License :: OSI Approved :: MIT License
Classifier: Operating System :: OS Independent
Requires-Python: >=3.6
